pytest_spark/__init__.py
pytest_spark/config.py
pytest_spark/fixtures.py
pytest_spark/home.py
pytest_spark/util.py
pytest_spark-0.8.0.dist-info/licenses/LICENSE
pytest_spark-0.8.0.dist-info/METADATA
pytest_spark-0.8.0.dist-info/WHEEL
pytest_spark-0.8.0.dist-info/entry_points.txt
pytest_spark-0.8.0.dist-info/top_level.txt
pytest_spark-0.8.0.dist-info/RECORD
