Metadata-Version: 2.4
Name: pytest-spark
Version: 0.8.0
Summary: pytest plugin to run the tests with support of pyspark.
Home-page: https://github.com/malexer/pytest-spark
Author: Alex (Oleksii) Markov
Author-email: alex@markovs.me
License: MIT
Keywords: pytest spark pyspark unittest test
Classifier: Development Status :: 4 - Beta
Classifier: Framework :: Pytest
Classifier: Intended Audience :: Developers
Classifier: Topic :: Software Development :: Libraries :: Python Modules
Classifier: License :: OSI Approved :: MIT License
Classifier: Programming Language :: Python :: 2
Classifier: Programming Language :: Python :: 2.7
Classifier: Programming Language :: Python :: 3
Classifier: Programming Language :: Python :: 3.2
Classifier: Programming Language :: Python :: 3.3
Classifier: Programming Language :: Python :: 3.4
Classifier: Programming Language :: Python :: 3.5
Classifier: Programming Language :: Python :: 3.6
Classifier: Topic :: Software Development :: Testing
License-File: LICENSE
Requires-Dist: pytest
Requires-Dist: findspark
Dynamic: author
Dynamic: author-email
Dynamic: classifier
Dynamic: description
Dynamic: home-page
Dynamic: keywords
Dynamic: license
Dynamic: license-file
Dynamic: requires-dist
Dynamic: summary
